munitests/__init__.py
munitests/main.py
munitests-0.3.0.dist-info/WHEEL
munitests-0.3.0.dist-info/METADATA
munitests-0.3.0.dist-info/RECORD
